README.md
setup.cfg
setup.py
bin/sign-in-sheet-generator
sign_in_sheet_generator/__init__.py
sign_in_sheet_generator/sign_in_sheet.py
sign_in_sheet_generator.egg-info/PKG-INFO
sign_in_sheet_generator.egg-info/SOURCES.txt
sign_in_sheet_generator.egg-info/dependency_links.txt
sign_in_sheet_generator.egg-info/not-zip-safe
sign_in_sheet_generator.egg-info/requires.txt
sign_in_sheet_generator.egg-info/top_level.txt