Metadata-Version: 1.0
Name: sign-in-sheet-generator
Version: 0.1
Summary: Sign-In Sheet Generator
Home-page: http://github.com/raymondberg/sign_in_sheet_generator
Author: Raymond Berg
Author-email: dev@raymondberg.com
License: MIT
Platform: UNKNOWN
